psycopgr/__init__.py
psycopgr/__version__.py
psycopgr/psycopgr.py
psycopgr-1.0.6.dist-info/LICENSE
psycopgr-1.0.6.dist-info/METADATA
psycopgr-1.0.6.dist-info/WHEEL
psycopgr-1.0.6.dist-info/top_level.txt
psycopgr-1.0.6.dist-info/RECORD
