Metadata-Version: 2.1
Name: psycopgr
Version: 1.0.6
Summary: A Python wrapper of pgRouting for routing from nodes to nodes on real map.
Home-page: https://github.com/herrkaefer/psycopgr
Author: Yang Liu
Author-email: gloolar@gmail.com
License: MIT
Platform: UNKNOWN
Classifier: License :: OSI Approved :: MIT License
Classifier: Programming Language :: Python
Classifier: Programming Language :: Python :: 3
Classifier: Programming Language :: Python :: 3.6
Classifier: Programming Language :: Python :: Implementation :: CPython
Classifier: Programming Language :: Python :: Implementation :: PyPy
Requires-Python: >=2.7
Requires-Dist: psycopg2
